[
    {
        "exit": "2B",
        "name": "Pan-Island Expressway (PIE)",
        "lat": "1.3140682265577024",
        "lng": "103.8747295770645"
    },
    {
        "exit": "5",
        "name": "Upper Paya Lebar Rd",
        "lat": "1.332211213834323",
        "lng": "103.88740368521212"
    },
    {
        "exit": "6",
        "name": "Bartley Rd East",
        "lat": "1.3368635841851557",
        "lng": "103.89509156680106"
    },
    {
        "exit": "9A",
        "name": "Tampines Rd",
        "lat": "1.359904083179361",
        "lng": "103.90332192516325"
    },
    {
        "exit": "9B",
        "name": "Buangkok Drive",
        "lat": "1.367623305222713",
        "lng": "103.90701264476775"
    },
    {
        "exit": "11",
        "name": "Tampines Expressway (TPE)",
        "lat": "1.3807543051095876",
        "lng": "103.91607448792456"
    }
]